fileshiftlib/__init__.py
fileshiftlib/__main__.py
fileshiftlib/fileshift.py
fileshiftlib-0.0.9.dist-info/licenses/LICENSE
fileshiftlib-0.0.9.dist-info/METADATA
fileshiftlib-0.0.9.dist-info/WHEEL
fileshiftlib-0.0.9.dist-info/top_level.txt
fileshiftlib-0.0.9.dist-info/RECORD
