Metadata-Version: 2.4
Name: fileshiftlib
Version: 0.0.9
Summary: SFTP client!
Author-email: Paulo Portela <portela.paulo@gmail.com>
Maintainer-email: Paulo Portela <portela.paulo@gmail.com>
License-Expression: BSD-3-Clause
Project-URL: Homepage, https://github.com/aghuttun/fileshiftlib
Project-URL: Documentation, https://github.com/aghuttun/fileshiftlib/blob/main/README.md
Keywords: SFTP,Python,FTP,File Transfer
Classifier: Programming Language :: Python :: 3.10
Classifier: Programming Language :: Python :: 3.11
Classifier: Programming Language :: Python :: 3.12
Classifier: Programming Language :: Python :: 3.13
Classifier: Programming Language :: Python :: Implementation :: CPython
Classifier: Intended Audience :: Developers
Classifier: Operating System :: POSIX :: Linux
Classifier: Operating System :: Microsoft :: Windows
Classifier: Operating System :: MacOS
Classifier: Operating System :: MacOS :: MacOS X
Requires-Python: >=3.10
License-File: LICENSE
Requires-Dist: paramiko>=3.0
Provides-Extra: dev
Requires-Dist: twine; extra == "dev"
Requires-Dist: build; extra == "dev"
Dynamic: license-file
